smunger/__init__.py
smunger/annotate.py
smunger/cli.py
smunger/console.py
smunger/constant.py
smunger/io.py
smunger/liftover.py
smunger/mapheader.py
smunger/plots.py
smunger/smunger.py
smunger-0.1.10.dist-info/LICENSE
smunger-0.1.10.dist-info/METADATA
smunger-0.1.10.dist-info/WHEEL
smunger-0.1.10.dist-info/entry_points.txt
smunger-0.1.10.dist-info/RECORD
