Metadata-Version: 2.1
Name: smunger
Version: 0.1.10
Summary: munger for GWAS summary statistics.
Home-page: https://github.com/jianhua/smunger
License: MIT
Author: Jianhua Wang
Author-email: jianhua.mert@gmail.com
Requires-Python: >=3.9,<3.13
Classifier: Development Status :: 2 - Pre-Alpha
Classifier: Intended Audience :: Developers
Classifier: License :: OSI Approved :: MIT License
Classifier: Natural Language :: English
Classifier: Programming Language :: Python :: 3
Classifier: Programming Language :: Python :: 3.9
Classifier: Programming Language :: Python :: 3.10
Classifier: Programming Language :: Python :: 3.11
Classifier: Programming Language :: Python :: 3.12
Classifier: Programming Language :: Python :: 3.8
Requires-Dist: liftover (>=1.1.16)
Requires-Dist: matplotlib (>=3.7.1)
Requires-Dist: numpy (>=1.26.0)
Requires-Dist: pandas (>=1.5.3)
Requires-Dist: pytabix (>=0.1)
Requires-Dist: requests (>=2.28.2)
Requires-Dist: rich (>=13.3.1)
Requires-Dist: scipy (>=1.10.1)
Requires-Dist: typer (>=0.7.0)
